pyciss/__init__.py
pyciss/_nbdev.py
pyciss/download.py
pyciss/index.py
pyciss/io.py
pyciss/opusapi.py
pyciss/pipeline.py
pyciss/plotting.py
pyciss/ringcube.py
pyciss/ringutils.py
pyciss/isis/__init__.py
pyciss/isis/cubefile.py
pyciss/isis/specialpixels.py
pyciss-0.13.2.dist-info/LICENSE
pyciss-0.13.2.dist-info/METADATA
pyciss-0.13.2.dist-info/WHEEL
pyciss-0.13.2.dist-info/entry_points.txt
pyciss-0.13.2.dist-info/top_level.txt
pyciss-0.13.2.dist-info/RECORD
