Metadata-Version: 2.1
Name: pyciss
Version: 0.13.2
Summary: Tools for Cassini ISS analysis
Home-page: https://github.com/michaelaye/pyciss/tree/master/
Author: Michael Aye
Author-email: kmichael.aye@gmail.com
License: Apache Software License 2.0
Keywords: planetary science,imaging
Platform: UNKNOWN
Classifier: Development Status :: 3 - Alpha
Classifier: Intended Audience :: Developers
Classifier: License :: OSI Approved :: Apache Software License
Classifier: Natural Language :: English
Classifier: Programming Language :: Python :: 3.8
Requires-Python: >=3.8
Requires-Dist: toml
Requires-Dist: pandas
Requires-Dist: requests
Requires-Dist: rasterio
Requires-Dist: scikit-image
Requires-Dist: planetarypy
